{
  "thread_title": "Daily Crypto Discussion - August 24, 2025 (GMT+0)",
  "thread_url": "https://www.reddit.com/r/CryptoCurrency/comments/1myh3c0/daily_crypto_discussion_august_24_2025_gmt0/",
  "generated_at_utc": "2025-08-24T07:14:22.310528Z",
  "results": {
    "BTC": 11,
    "ETH": 7,
    "XRP": 1,
    "LINK": 1,
    "PEPE": 1,
    "BNB": 1,
    "LTC": 1,
    "SOL": 1,
    "TON": 1
  },
  "results_list": [
    {
      "symbol": "BTC",
      "name": "Bitcoin",
      "count": 11
    },
    {
      "symbol": "ETH",
      "name": "Ethereum",
      "count": 7
    },
    {
      "symbol": "XRP",
      "name": "XRP",
      "count": 1
    },
    {
      "symbol": "LINK",
      "name": "Chainlink",
      "count": 1
    },
    {
      "symbol": "PEPE",
      "name": "PEPE",
      "count": 1
    },
    {
      "symbol": "BNB",
      "name": "BNB",
      "count": 1
    },
    {
      "symbol": "LTC",
      "name": "Litecoin",
      "count": 1
    },
    {
      "symbol": "SOL",
      "name": "Solana",
      "count": 1
    },
    {
      "symbol": "TON",
      "name": "Toncoin",
      "count": 1
    }
  ]
}