{
  "thread_title": "Daily Crypto Discussion - December 25, 2025 (GMT+0)",
  "thread_url": "https://www.reddit.com/r/CryptoCurrency/comments/1pv1sk4/daily_crypto_discussion_december_25_2025_gmt0/",
  "generated_at_utc": "2025-12-25T18:24:44.359759Z",
  "results": {
    "BTC": 3,
    "SHIB": 1,
    "MELANIA": 1,
    "ADA": 1
  },
  "results_list": [
    {
      "symbol": "BTC",
      "name": "Bitcoin",
      "count": 3
    },
    {
      "symbol": "SHIB",
      "name": "Shiba Inu",
      "count": 1
    },
    {
      "symbol": "MELANIA",
      "name": "",
      "count": 1
    },
    {
      "symbol": "ADA",
      "name": "Cardano",
      "count": 1
    }
  ]
}