{
  "thread_title": "Daily Crypto Discussion - November 24, 2025 (GMT+0)",
  "thread_url": "https://www.reddit.com/r/CryptoCurrency/comments/1p53enx/daily_crypto_discussion_november_24_2025_gmt0/",
  "generated_at_utc": "2025-11-24T20:19:15.853236Z",
  "results": {
    "BTC": 50,
    "ETH": 9,
    "LINK": 2,
    "SOL": 2,
    "ETC": 2,
    "SUI": 1,
    "NEAR": 1,
    "ADA": 1,
    "ERB": 1
  },
  "results_list": [
    {
      "symbol": "BTC",
      "name": "Bitcoin",
      "count": 50
    },
    {
      "symbol": "ETH",
      "name": "Ethereum",
      "count": 9
    },
    {
      "symbol": "LINK",
      "name": "Chainlink",
      "count": 2
    },
    {
      "symbol": "SOL",
      "name": "Solana",
      "count": 2
    },
    {
      "symbol": "ETC",
      "name": "Ethereum Classic",
      "count": 2
    },
    {
      "symbol": "SUI",
      "name": "Sui",
      "count": 1
    },
    {
      "symbol": "NEAR",
      "name": "NEAR",
      "count": 1
    },
    {
      "symbol": "ADA",
      "name": "Cardano",
      "count": 1
    },
    {
      "symbol": "ERB",
      "name": "",
      "count": 1
    }
  ]
}