{
  "thread_title": "Daily Crypto Discussion - January 14, 2026 (GMT+0)",
  "thread_url": "https://www.reddit.com/r/CryptoCurrency/comments/1qc98k3/daily_crypto_discussion_january_14_2026_gmt0/",
  "generated_at_utc": "2026-01-14T08:25:55.888984Z",
  "results": {
    "BTC": 6,
    "XMR": 4,
    "BCH": 2,
    "XRP": 2,
    "ETC": 1,
    "SOL": 1,
    "DOT": 1,
    "ETH": 1,
    "CRO": 1,
    "IP": 1
  },
  "results_list": [
    {
      "symbol": "BTC",
      "name": "Bitcoin",
      "count": 6
    },
    {
      "symbol": "XMR",
      "name": "Monero",
      "count": 4
    },
    {
      "symbol": "BCH",
      "name": "Bitcoin Cash",
      "count": 2
    },
    {
      "symbol": "XRP",
      "name": "XRP",
      "count": 2
    },
    {
      "symbol": "ETC",
      "name": "Ethereum Classic",
      "count": 1
    },
    {
      "symbol": "SOL",
      "name": "Solana",
      "count": 1
    },
    {
      "symbol": "DOT",
      "name": "Polkadot",
      "count": 1
    },
    {
      "symbol": "ETH",
      "name": "Ethereum",
      "count": 1
    },
    {
      "symbol": "CRO",
      "name": "Cronos",
      "count": 1
    },
    {
      "symbol": "IP",
      "name": "",
      "count": 1
    }
  ]
}