{
  "thread_title": "Daily Crypto Discussion - September 17, 2025 (GMT+0)",
  "thread_url": "https://www.reddit.com/r/CryptoCurrency/comments/1niy0m5/daily_crypto_discussion_september_17_2025_gmt0/",
  "generated_at_utc": "2025-09-17T20:16:30.370613Z",
  "results": {
    "BTC": 30,
    "ETH": 15,
    "BNB": 3,
    "XRP": 3,
    "ADA": 3,
    "DOT": 3,
    "MANA": 3,
    "SOL": 2,
    "SAND": 1,
    "GMX": 1,
    "ETC": 1,
    "ALGO": 1,
    "LINK": 1,
    "HBAR": 1,
    "XLM": 1,
    "MKR": 1,
    "LTC": 1
  },
  "results_list": [
    {
      "symbol": "BTC",
      "name": "Bitcoin",
      "count": 30
    },
    {
      "symbol": "ETH",
      "name": "Ethereum",
      "count": 15
    },
    {
      "symbol": "BNB",
      "name": "BNB",
      "count": 3
    },
    {
      "symbol": "XRP",
      "name": "XRP",
      "count": 3
    },
    {
      "symbol": "ADA",
      "name": "Cardano",
      "count": 3
    },
    {
      "symbol": "DOT",
      "name": "Polkadot",
      "count": 3
    },
    {
      "symbol": "MANA",
      "name": "Decentraland",
      "count": 3
    },
    {
      "symbol": "SOL",
      "name": "Solana",
      "count": 2
    },
    {
      "symbol": "SAND",
      "name": "The Sandbox",
      "count": 1
    },
    {
      "symbol": "GMX",
      "name": "GMX",
      "count": 1
    },
    {
      "symbol": "ETC",
      "name": "Ethereum Classic",
      "count": 1
    },
    {
      "symbol": "ALGO",
      "name": "Algorand",
      "count": 1
    },
    {
      "symbol": "LINK",
      "name": "Chainlink",
      "count": 1
    },
    {
      "symbol": "HBAR",
      "name": "Hedera",
      "count": 1
    },
    {
      "symbol": "XLM",
      "name": "Stellar",
      "count": 1
    },
    {
      "symbol": "MKR",
      "name": "Maker",
      "count": 1
    },
    {
      "symbol": "LTC",
      "name": "Litecoin",
      "count": 1
    }
  ]
}