{
  "thread_title": "Daily Crypto Discussion - February 4, 2026 (GMT+0)",
  "thread_url": "https://www.reddit.com/r/CryptoCurrency/comments/1qva66z/daily_crypto_discussion_february_4_2026_gmt0/",
  "generated_at_utc": "2026-02-04T14:00:53.802999Z",
  "results": {
    "BTC": 18,
    "SOL": 11,
    "ETH": 8,
    "ETC": 2,
    "SUI": 1,
    "LINK": 1,
    "XRP": 1
  },
  "results_list": [
    {
      "symbol": "BTC",
      "name": "Bitcoin",
      "count": 18
    },
    {
      "symbol": "SOL",
      "name": "Solana",
      "count": 11
    },
    {
      "symbol": "ETH",
      "name": "Ethereum",
      "count": 8
    },
    {
      "symbol": "ETC",
      "name": "Ethereum Classic",
      "count": 2
    },
    {
      "symbol": "SUI",
      "name": "Sui",
      "count": 1
    },
    {
      "symbol": "LINK",
      "name": "Chainlink",
      "count": 1
    },
    {
      "symbol": "XRP",
      "name": "XRP",
      "count": 1
    }
  ]
}