{
  "thread_title": "Daily Crypto Discussion - January 24, 2026 (GMT+0)",
  "thread_url": "https://www.reddit.com/r/CryptoCurrency/comments/1ql8rcg/daily_crypto_discussion_january_24_2026_gmt0/",
  "generated_at_utc": "2026-01-24T21:15:24.461596Z",
  "results": {
    "BTC": 36,
    "ETH": 3,
    "ETC": 2,
    "NEAR": 1
  },
  "results_list": [
    {
      "symbol": "BTC",
      "name": "Bitcoin",
      "count": 36
    },
    {
      "symbol": "ETH",
      "name": "Ethereum",
      "count": 3
    },
    {
      "symbol": "ETC",
      "name": "Ethereum Classic",
      "count": 2
    },
    {
      "symbol": "NEAR",
      "name": "NEAR",
      "count": 1
    }
  ]
}