{
  "thread_title": "Daily Crypto Discussion - December 22, 2025 (GMT+0)",
  "thread_url": "https://www.reddit.com/r/CryptoCurrency/comments/1psm919/daily_crypto_discussion_december_22_2025_gmt0/",
  "generated_at_utc": "2025-12-22T13:31:45.540958Z",
  "results": {
    "BTC": 7,
    "ETH": 5,
    "XMR": 4,
    "ETC": 2,
    "NEAR": 2,
    "ADA": 2,
    "EGLD": 1,
    "BCH": 1,
    "DOT": 1
  },
  "results_list": [
    {
      "symbol": "BTC",
      "name": "Bitcoin",
      "count": 7
    },
    {
      "symbol": "ETH",
      "name": "Ethereum",
      "count": 5
    },
    {
      "symbol": "XMR",
      "name": "Monero",
      "count": 4
    },
    {
      "symbol": "ETC",
      "name": "Ethereum Classic",
      "count": 2
    },
    {
      "symbol": "NEAR",
      "name": "NEAR",
      "count": 2
    },
    {
      "symbol": "ADA",
      "name": "Cardano",
      "count": 2
    },
    {
      "symbol": "EGLD",
      "name": "MultiversX (EGLD)",
      "count": 1
    },
    {
      "symbol": "BCH",
      "name": "Bitcoin Cash",
      "count": 1
    },
    {
      "symbol": "DOT",
      "name": "Polkadot",
      "count": 1
    }
  ]
}