{
  "thread_title": "Daily Crypto Discussion - September 18, 2025 (GMT+0)",
  "thread_url": "https://www.reddit.com/r/CryptoCurrency/comments/1njtf17/daily_crypto_discussion_september_18_2025_gmt0/",
  "generated_at_utc": "2025-09-18T13:24:44.514904Z",
  "results": {
    "BNB": 18,
    "BTC": 16,
    "ETH": 7,
    "SOL": 4,
    "ETC": 3,
    "AVAX": 2,
    "NEAR": 2,
    "LINK": 1,
    "ADA": 1
  },
  "results_list": [
    {
      "symbol": "BNB",
      "name": "BNB",
      "count": 18
    },
    {
      "symbol": "BTC",
      "name": "Bitcoin",
      "count": 16
    },
    {
      "symbol": "ETH",
      "name": "Ethereum",
      "count": 7
    },
    {
      "symbol": "SOL",
      "name": "Solana",
      "count": 4
    },
    {
      "symbol": "ETC",
      "name": "Ethereum Classic",
      "count": 3
    },
    {
      "symbol": "AVAX",
      "name": "Avalanche",
      "count": 2
    },
    {
      "symbol": "NEAR",
      "name": "NEAR",
      "count": 2
    },
    {
      "symbol": "LINK",
      "name": "Chainlink",
      "count": 1
    },
    {
      "symbol": "ADA",
      "name": "Cardano",
      "count": 1
    }
  ]
}