{
  "thread_title": "Daily Crypto Discussion - September 6, 2025 (GMT+0)",
  "thread_url": "https://www.reddit.com/r/CryptoCurrency/comments/1n9l3rc/daily_crypto_discussion_september_6_2025_gmt0/",
  "generated_at_utc": "2025-09-06T20:14:47.150191Z",
  "results": {
    "BTC": 18,
    "ETH": 10,
    "LINK": 2,
    "PEPE": 2,
    "OP": 1,
    "KTA": 1,
    "LTC": 1,
    "PUMP": 1
  },
  "results_list": [
    {
      "symbol": "BTC",
      "name": "Bitcoin",
      "count": 18
    },
    {
      "symbol": "ETH",
      "name": "Ethereum",
      "count": 10
    },
    {
      "symbol": "LINK",
      "name": "Chainlink",
      "count": 2
    },
    {
      "symbol": "PEPE",
      "name": "PEPE",
      "count": 2
    },
    {
      "symbol": "OP",
      "name": "Optimism",
      "count": 1
    },
    {
      "symbol": "KTA",
      "name": "",
      "count": 1
    },
    {
      "symbol": "LTC",
      "name": "Litecoin",
      "count": 1
    },
    {
      "symbol": "PUMP",
      "name": "",
      "count": 1
    }
  ]
}