{
  "thread_title": "Daily Crypto Discussion - February 2, 2026 (GMT+0)",
  "thread_url": "https://www.reddit.com/r/CryptoCurrency/comments/1qtgmr9/daily_crypto_discussion_february_2_2026_gmt0/",
  "generated_at_utc": "2026-02-02T12:52:22.828687Z",
  "results": {
    "BTC": 68,
    "ETH": 37,
    "LINK": 4,
    "SHIB": 2,
    "DOT": 2,
    "ETC": 2,
    "MKR": 1,
    "SOL": 1,
    "32": 1,
    "SAND": 1,
    "XMR": 1
  },
  "results_list": [
    {
      "symbol": "BTC",
      "name": "Bitcoin",
      "count": 68
    },
    {
      "symbol": "ETH",
      "name": "Ethereum",
      "count": 37
    },
    {
      "symbol": "LINK",
      "name": "Chainlink",
      "count": 4
    },
    {
      "symbol": "SHIB",
      "name": "Shiba Inu",
      "count": 2
    },
    {
      "symbol": "DOT",
      "name": "Polkadot",
      "count": 2
    },
    {
      "symbol": "ETC",
      "name": "Ethereum Classic",
      "count": 2
    },
    {
      "symbol": "MKR",
      "name": "Maker",
      "count": 1
    },
    {
      "symbol": "SOL",
      "name": "Solana",
      "count": 1
    },
    {
      "symbol": "32",
      "name": "",
      "count": 1
    },
    {
      "symbol": "SAND",
      "name": "The Sandbox",
      "count": 1
    },
    {
      "symbol": "XMR",
      "name": "Monero",
      "count": 1
    }
  ]
}